LICENSE
MANIFEST.in
README.rst
setup.py
mcloud/__init__.py
mcloud/application.py
mcloud/attach.py
mcloud/config.py
mcloud/container.py
mcloud/deployment.py
mcloud/events.py
mcloud/interrupt.py
mcloud/logo.py
mcloud/main.py
mcloud/metadata.py
mcloud/plugin.py
mcloud/remote.py
mcloud/rpc_client.py
mcloud/rpc_server.py
mcloud/service.py
mcloud/shell.py
mcloud/ssl.py
mcloud/sync.py
mcloud/tasks.py
mcloud/test_utils.py
mcloud/txdocker.py
mcloud/txhttp.py
mcloud/util.py
mcloud/version.py
mcloud.egg-info/PKG-INFO
mcloud.egg-info/SOURCES.txt
mcloud.egg-info/dependency_links.txt
mcloud.egg-info/entry_points.txt
mcloud.egg-info/not-zip-safe
mcloud.egg-info/requires.txt
mcloud.egg-info/top_level.txt
mcloud/plugins/__init__.py
mcloud/plugins/dns.py
mcloud/plugins/hosts.py
mcloud/plugins/monitor.py
mcloud/static/.bowerrc
mcloud/static/.gitignore
mcloud/static/bower.json
mcloud/static/gulpfile.js
mcloud/static/package.json
mcloud/static/client/apple-touch-icon-precomposed.png
mcloud/static/client/favicon.ico
mcloud/static/client/humans.txt
mcloud/static/client/index.html
mcloud/static/client/assets/images/angular-logo.png
mcloud/static/client/assets/images/bower-logo.png
mcloud/static/client/assets/images/gulp-logo.png
mcloud/static/client/src/app/app.js
mcloud/static/client/src/app/getting-started/getting-started.js
mcloud/static/client/src/app/getting-started/getting-started.tpl.html
mcloud/static/client/src/app/home/home.js
mcloud/static/client/src/app/home/home.tpl.html
mcloud/static/client/src/common/footer.js
mcloud/static/client/src/common/footer.tpl.html
mcloud/static/client/src/common/header.js
mcloud/static/client/src/common/header.tpl.html
mcloud/static/client/src/common/directives/version.js
mcloud/static/client/src/common/filters/uppercase.js
mcloud/static/client/src/common/interceptors/httpInterceptor.js
mcloud/static/client/src/common/services/dataService.js
mcloud/static/client/src/scss/main.scss
mcloud/static/client/test/utils.js
mcloud/static/client/test/e2e/01.home.scenario.js
mcloud/static/client/test/screenshots/README.md
mcloud/static/client/test/unit-results/README.md
mcloud/static/client/test/unit/app/app.spec.js
